mlsgrid_api/__init__.py
mlsgrid_api/mlsgrid_api.py
mlsgrid_api-0.0.14.dist-info/LICENSE
mlsgrid_api-0.0.14.dist-info/METADATA
mlsgrid_api-0.0.14.dist-info/WHEEL
mlsgrid_api-0.0.14.dist-info/top_level.txt
mlsgrid_api-0.0.14.dist-info/RECORD
