Metadata-Version: 2.1
Name: mlsgrid-api
Version: 0.0.14
Summary: Python library for the MLSGrid API
Author-email: captivus <366332+captivus@users.noreply.github.com>
License: GPL-3.0-only
Project-URL: Homepage, https://github.com/captivus/mlsgrid_api
Classifier: Programming Language :: Python :: 3
Classifier: License :: OSI Approved :: GNU General Public License v3 (GPLv3)
Classifier: Operating System :: OS Independent
Requires-Python: >=3.7
License-File: LICENSE
Requires-Dist: requests
Requires-Dist: python-dotenv
Requires-Dist: pytest
Requires-Dist: ratelimit
Requires-Dist: pytz
